cmd_utils/__init__.py
cmd_utils/cmd.py
cmd_utils-1.0.0.dist-info/LICENSE
cmd_utils-1.0.0.dist-info/METADATA
cmd_utils-1.0.0.dist-info/WHEEL
cmd_utils-1.0.0.dist-info/top_level.txt
cmd_utils-1.0.0.dist-info/RECORD
